warranty_claim_ai_engine/Agent.py
warranty_claim_ai_engine/__init__.py
warranty_claim_ai_engine/model.py
warranty_claim_ai_engine/ocr.py
warranty_claim_ai_engine/rag_system.py
warranty_claim_ai_engine/test.py
warranty_claim_ai_engine-0.1.6.dist-info/licenses/LICENSE
warranty_claim_ai_engine-0.1.6.dist-info/METADATA
warranty_claim_ai_engine-0.1.6.dist-info/WHEEL
warranty_claim_ai_engine-0.1.6.dist-info/top_level.txt
warranty_claim_ai_engine-0.1.6.dist-info/RECORD
