Metadata-Version: 2.4
Name: warranty-claim-ai-engine
Version: 0.1.6
Summary: A GenAI-powered SDK to automate warranty claim processing.
Author-email: 54g0 <sagar8296d@gmail.com>
License: MIT License
Project-URL: Homepage, https://github.com/54g0/Warranty-Claim-AI-Agent
Classifier: Programming Language :: Python :: 3
Classifier: License :: OSI Approved :: MIT License
Classifier: Operating System :: OS Independent
Requires-Python: >=3.8
License-File: LICENSE
Requires-Dist: langchain
Requires-Dist: langchain-google-genai
Requires-Dist: langchain-openai
Requires-Dist: langchain-community
Requires-Dist: langgraph
Requires-Dist: langchain_groq
Requires-Dist: langsmith
Requires-Dist: openai
Requires-Dist: google-generativeai
Requires-Dist: pandas
Requires-Dist: numpy
Requires-Dist: pillow
Requires-Dist: pytesseract
Requires-Dist: opencv-python
Requires-Dist: scikit-learn
Requires-Dist: faiss-cpu
Requires-Dist: sentence-transformers
Requires-Dist: plotly
Requires-Dist: python-dotenv
Requires-Dist: pydantic
Requires-Dist: typing-extensions
Requires-Dist: requests
Requires-Dist: groq
Requires-Dist: huggingface-hub
Requires-Dist: transformers
Requires-Dist: easyocr
Dynamic: license-file
